{
    "Birthday": 7,
    "Birthmonth": 6,
    "Birthyear": 468,
    "Birthplace": "Sky Realm",
    "Birthplace_JP": "空の世界",
    "Birthlocation": "Unknown Town",
    "Birthlocation_JP": "不詳の地",
    "Mom": "Vain Witch",
    "Mom_JP": "虚栄心の強い魔女",
    "Dad": "Egotistical Wizard",
    "Dad_JP": "自負の強い魔導士",
    "Background": "An ordinary girl born into an extraordinary family of mages, Nier spent her childhood starved for acceptance. Now as a young woman contracted to the primal beast Death, she flies into a murderous rage when scorned. Nier found herself in Ylva, lost, confused, but certainly not alone.",
    "Background_JP": "星晶獣「デス」と契約を交わした少女。有能な魔法使いを代々輩出してきた伝統ある家に生まれた。自分の存在を肯定してほしいという強い欲求を持っており、激しく否定された際は、無秩序な加虐性をのぞかせることもある。\n今ノースティリスに現れたニーアは、戸惑いながらも一人ではなかった"
}